{
  "resourceType": "StructureDefinition",
  "id": "mii-pr-mikrobio-empfindlichkeit",
  "url": "https://www.medizininformatik-initiative.de/fhir/modul-mikrobio/StructureDefinition/mii-pr-mikrobio-empfindlichkeit",
  "name": "MII_PR_Mikrobio_Empfindlichkeit",
  "title": "MII PR Mikrobio Empfindlichkeit",
  "status": "active",
  "version": "2025.0.0",
  "experimental": false,
  "publisher": "https://www.Medizininformatik-Initiative.de",
  "description": "This profile describes a susceptibility test in microbiology",
  "purpose": "Dieses Profil beschreibt ein Empfindlichkeit Test der Medizininformatik-Initiative.",
  "fhirVersion": "4.0.1",
  "kind": "resource",
  "abstract": false,
  "type": "Observation",
  "baseDefinition": "http://hl7.org/fhir/StructureDefinition/Observation",
  "derivation": "constraint",
  "differential": {
    "element": [
      {
        "id": "Observation",
        "path": "Observation",
        "constraint": [
          {
            "key": "mii-lab-2",
            "severity": "error",
            "human": "Falls kein Laborwert verfügbar ist, muss eine dataAbsentReason angegeben werden",
            "expression": "value.exists().not() implies dataAbsentReason.exists()"
          }
        ]
      },
      {
        "id": "Observation.id",
        "path": "Observation.id",
        "mustSupport": true
      },
      {
        "id": "Observation.meta",
        "path": "Observation.meta",
        "mustSupport": true
      },
      {
        "id": "Observation.meta.source",
        "path": "Observation.meta.source",
        "mustSupport": true
      },
      {
        "id": "Observation.meta.profile",
        "path": "Observation.meta.profile",
        "mustSupport": true
      },
      {
        "id": "Observation.identifier",
        "path": "Observation.identifier",
        "slicing": {
          "discriminator": [
            {
              "type": "pattern",
              "path": "type"
            }
          ],
          "rules": "open"
        },
        "min": 1,
        "mustSupport": true
      },
      {
        "id": "Observation.identifier:analyseBefundCode",
        "path": "Observation.identifier",
        "sliceName": "analyseBefundCode",
        "min": 1,
        "max": "1",
        "mustSupport": true
      },
      {
        "id": "Observation.identifier:analyseBefundCode.type",
        "path": "Observation.identifier.type",
        "min": 1,
        "patternCodeableConcept": {
          "coding": [
            {
              "system": "http://terminology.hl7.org/CodeSystem/v2-0203",
              "code": "OBI"
            }
          ]
        },
        "mustSupport": true
      },
      {
        "id": "Observation.identifier:analyseBefundCode.type.coding",
        "path": "Observation.identifier.type.coding",
        "slicing": {
          "discriminator": [
            {
              "type": "value",
              "path": "system"
            }
          ],
          "rules": "open"
        },
        "min": 1,
        "mustSupport": true
      },
      {
        "id": "Observation.identifier:analyseBefundCode.type.coding:observationInstanceV2",
        "path": "Observation.identifier.type.coding",
        "sliceName": "observationInstanceV2",
        "min": 1,
        "max": "1",
        "mustSupport": true
      },
      {
        "id": "Observation.identifier:analyseBefundCode.type.coding:observationInstanceV2.system",
        "path": "Observation.identifier.type.coding.system",
        "min": 1,
        "fixedUri": "http://terminology.hl7.org/CodeSystem/v2-0203",
        "mustSupport": true
      },
      {
        "id": "Observation.identifier:analyseBefundCode.type.coding:observationInstanceV2.code",
        "path": "Observation.identifier.type.coding.code",
        "min": 1,
        "fixedCode": "OBI",
        "mustSupport": true
      },
      {
        "id": "Observation.identifier:analyseBefundCode.system",
        "path": "Observation.identifier.system",
        "min": 1,
        "mustSupport": true
      },
      {
        "id": "Observation.identifier:analyseBefundCode.value",
        "path": "Observation.identifier.value",
        "min": 1,
        "mustSupport": true
      },
      {
        "id": "Observation.identifier:analyseBefundCode.assigner",
        "path": "Observation.identifier.assigner",
        "min": 1,
        "type": [
          {
            "code": "Reference",
            "profile": [
              "https://www.medizininformatik-initiative.de/fhir/core/StructureDefinition/MII-Reference"
            ]
          }
        ],
        "mustSupport": true
      },
      {
        "id": "Observation.status",
        "path": "Observation.status",
        "mustSupport": true
      },
      {
        "id": "Observation.category",
        "path": "Observation.category",
        "min": 1,
        "mustSupport": true
      },
      {
        "id": "Observation.category.coding",
        "path": "Observation.category.coding",
        "slicing": {
          "discriminator": [
            {
              "type": "pattern",
              "path": "$this"
            }
          ],
          "rules": "open"
        },
        "min": 3,
        "mustSupport": true
      },
      {
        "id": "Observation.category.coding:loinc-observation",
        "path": "Observation.category.coding",
        "sliceName": "loinc-observation",
        "min": 1,
        "max": "1",
        "patternCoding": {
          "system": "http://loinc.org",
          "code": "26436-6"
        },
        "mustSupport": true
      },
      {
        "id": "Observation.category.coding:observation-category",
        "path": "Observation.category.coding",
        "sliceName": "observation-category",
        "min": 1,
        "max": "1",
        "patternCoding": {
          "system": "http://terminology.hl7.org/CodeSystem/observation-category",
          "code": "laboratory"
        },
        "mustSupport": true
      },
      {
        "id": "Observation.category.coding:loinc-microbiology-studies",
        "path": "Observation.category.coding",
        "sliceName": "loinc-microbiology-studies",
        "min": 1,
        "max": "1",
        "patternCoding": {
          "system": "http://loinc.org",
          "code": "18725-2"
        },
        "mustSupport": true
      },
      {
        "id": "Observation.code",
        "path": "Observation.code",
        "mustSupport": true,
        "binding": {
          "strength": "required",
          "valueSet": "https://www.medizininformatik-initiative.de/fhir/modul-mikrobio/ValueSet/mii-vs-mikrobio-empfindlichkeit-phenotyp-loinc"
        }
      },
      {
        "id": "Observation.subject",
        "path": "Observation.subject",
        "min": 1,
        "type": [
          {
            "code": "Reference",
            "profile": [
              "https://www.medizininformatik-initiative.de/fhir/core/StructureDefinition/MII-Reference"
            ]
          }
        ],
        "mustSupport": true
      },
      {
        "id": "Observation.encounter",
        "path": "Observation.encounter",
        "mustSupport": true
      },
      {
        "id": "Observation.effective[x]",
        "path": "Observation.effective[x]",
        "min": 1,
        "type": [
          {
            "code": "dateTime"
          }
        ],
        "constraint": [
          {
            "key": "mii-lab-1",
            "severity": "error",
            "human": "Datetime must be at least to day",
            "expression": "($this as dateTime).hasValue() implies ($this as dateTime).toString().length() >= 8"
          }
        ],
        "mustSupport": true
      },
      {
        "id": "Observation.effective[x].extension:QuelleKlinischesBezugsdatum",
        "path": "Observation.effective[x].extension",
        "sliceName": "QuelleKlinischesBezugsdatum",
        "max": "1",
        "type": [
          {
            "code": "Extension",
            "profile": [
              "https://www.medizininformatik-initiative.de/fhir/core/modul-labor/StructureDefinition/QuelleKlinischesBezugsdatum"
            ]
          }
        ],
        "mustSupport": true
      },
      {
        "id": "Observation.effective[x].extension:QuelleKlinischesBezugsdatum.url",
        "path": "Observation.effective[x].extension.url",
        "fixedUri": "https://www.medizininformatik-initiative.de/fhir/core/modul-labor/StructureDefinition/QuelleKlinischesBezugsdatum"
      },
      {
        "id": "Observation.issued",
        "path": "Observation.issued",
        "mustSupport": true
      },
      {
        "id": "Observation.value[x]",
        "path": "Observation.value[x]",
        "type": [
          {
            "code": "Quantity"
          }
        ],
        "mustSupport": true
      },
      {
        "id": "Observation.value[x].code",
        "path": "Observation.value[x].code",
        "binding": {
          "strength": "required",
          "valueSet": "https://www.medizininformatik-initiative.de/fhir/modul-mikrobio/ValueSet/mii-vs-empfindlichkeit-einheiten-ucum"
        }
      },
      {
        "id": "Observation.dataAbsentReason",
        "path": "Observation.dataAbsentReason",
        "mustSupport": true
      },
      {
        "id": "Observation.interpretation",
        "path": "Observation.interpretation",
        "slicing": {
          "discriminator": [
            {
              "type": "pattern",
              "path": "$this"
            }
          ],
          "rules": "open"
        },
        "max": "1",
        "mustSupport": true
      },
      {
        "id": "Observation.interpretation:EUCAST",
        "path": "Observation.interpretation",
        "sliceName": "EUCAST",
        "max": "1",
        "binding": {
          "strength": "required",
          "valueSet": "https://www.medizininformatik-initiative.de/fhir/modul-mikrobio/ValueSet/mii-vs-mikrobio-eucast-snomedct"
        }
      },
      {
        "id": "Observation.interpretation:EUCAST.coding.version",
        "path": "Observation.interpretation.coding.version",
        "min": 1
      },
      {
        "id": "Observation.interpretation:CLSI",
        "path": "Observation.interpretation",
        "sliceName": "CLSI",
        "label": "CLSI",
        "max": "1",
        "binding": {
          "strength": "required",
          "valueSet": "https://www.medizininformatik-initiative.de/fhir/modul-mikrobio/ValueSet/mii-vs-mikrobio-clsi-hl7"
        }
      },
      {
        "id": "Observation.interpretation:CLSI.coding.version",
        "path": "Observation.interpretation.coding.version",
        "min": 1
      },
      {
        "id": "Observation.note",
        "path": "Observation.note",
        "mustSupport": true
      },
      {
        "id": "Observation.bodySite",
        "path": "Observation.bodySite",
        "max": "0"
      },
      {
        "id": "Observation.method",
        "path": "Observation.method",
        "mustSupport": true
      },
      {
        "id": "Observation.specimen",
        "path": "Observation.specimen",
        "min": 1,
        "mustSupport": true
      },
      {
        "id": "Observation.specimen.reference",
        "path": "Observation.specimen.reference",
        "mustSupport": true
      },
      {
        "id": "Observation.specimen.identifier",
        "path": "Observation.specimen.identifier",
        "mustSupport": true
      },
      {
        "id": "Observation.device",
        "path": "Observation.device",
        "mustSupport": true
      },
      {
        "id": "Observation.referenceRange",
        "path": "Observation.referenceRange",
        "mustSupport": true
      },
      {
        "id": "Observation.component.value[x]",
        "path": "Observation.component.value[x]",
        "type": [
          {
            "code": "CodeableConcept"
          }
        ]
      }
    ]
  }
}